setup.py
sfl_distributions/Binomialdistribution.py
sfl_distributions/Gaussiandistribution.py
sfl_distributions/Generaldistribution.py
sfl_distributions/__init__.py
sfl_distributions.egg-info/PKG-INFO
sfl_distributions.egg-info/SOURCES.txt
sfl_distributions.egg-info/dependency_links.txt
sfl_distributions.egg-info/not-zip-safe
sfl_distributions.egg-info/top_level.txt