Metadata-Version: 1.0
Name: sfl-distributions
Version: 0.1
Summary: Gaussian and Binomial distributions
Home-page: UNKNOWN
Author: Sergio Falcón
Author-email: UNKNOWN
License: UNKNOWN
Platform: UNKNOWN
